pywoodway/__init__.py
pywoodway/treadmill.py
pyWoodway-0.2.4.dist-info/LICENSE
pyWoodway-0.2.4.dist-info/METADATA
pyWoodway-0.2.4.dist-info/WHEEL
pyWoodway-0.2.4.dist-info/top_level.txt
pyWoodway-0.2.4.dist-info/RECORD
