Metadata-Version: 2.1
Name: pyWoodway
Version: 0.2.4
Summary: Communicate with your Woodway treadmill in your Python scripts.
Home-page: https://github.com/Munroe-Meyer-Institute-VR-Laboratory/pyWoodway
Author: Walker Arce
Author-email: walker.arce@unmc.edu
License: MIT
Keywords: Woodway treadmill biomechanics
Classifier: License :: OSI Approved :: MIT License
Classifier: Programming Language :: Python :: 3.8
License-File: LICENSE
Requires-Dist: pyserial
